uai_openlabel/__init__.py
uai_openlabel/coordinate_system.py
uai_openlabel/data_types/__init__.py
uai_openlabel/data_types/data_pointer_types.py
uai_openlabel/data_types/data_to_pointer_type_mapping.py
uai_openlabel/data_types/generic_data.py
uai_openlabel/data_types/geometric_data.py
uai_openlabel/elements/__init__.py
uai_openlabel/elements/action.py
uai_openlabel/elements/context.py
uai_openlabel/elements/element_data_pointer.py
uai_openlabel/elements/event.py
uai_openlabel/elements/object.py
uai_openlabel/elements/relation.py
uai_openlabel/frame.py
uai_openlabel/frame_interval.py
uai_openlabel/metadata.py
uai_openlabel/official_schema/openlabel_json_schema.json
uai_openlabel/ontology.py
uai_openlabel/openlabel.py
uai_openlabel/py.typed
uai_openlabel/serializer.py
uai_openlabel/stream/__init__.py
uai_openlabel/stream/camera_intrinsics.py
uai_openlabel/stream/stream.py
uai_openlabel/stream/stream_properties.py
uai_openlabel/tag.py
uai_openlabel/transform.py
uai_openlabel/types_and_constants.py
uai_openlabel/utils.py
uai_openlabel-0.3.8.dist-info/LICENSE
uai_openlabel-0.3.8.dist-info/METADATA
uai_openlabel-0.3.8.dist-info/WHEEL
uai_openlabel-0.3.8.dist-info/RECORD
