Metadata-Version: 2.1
Name: uai_openlabel
Version: 0.3.8
Summary: A library to produce and parse JSONs in the OpenLABEL format.
Home-page: https://github.com/understand-ai/uai_openlabel
License: MIT
Keywords: ASAM OpenLABEL
Author: understand.ai
Author-email: postmaster@understand.ai
Requires-Python: >=3.9,<3.13
Classifier: License :: OSI Approved :: MIT License
Classifier: Programming Language :: Python :: 3
Classifier: Programming Language :: Python :: 3.9
Classifier: Programming Language :: Python :: 3.10
Classifier: Programming Language :: Python :: 3.11
Classifier: Programming Language :: Python :: 3.12
Requires-Dist: apischema (>=0.18.0,<0.19.0)
Project-URL: Repository, https://github.com/understand-ai/uai_openlabel
